vex_python/__init__.py
vex_python/_vex.pyd
vex_python/boost_python312-vc143-mt-x64-1_90.dll
vex_python/liblz4.dll
vex_python-0.1.44.dist-info/METADATA
vex_python-0.1.44.dist-info/WHEEL
vex_python-0.1.44.dist-info/top_level.txt
vex_python-0.1.44.dist-info/RECORD
