Metadata-Version: 2.4
Name: vex-python
Version: 0.1.44
Summary: C++ Python bindings for Vex
Home-page: https://github.com/Hitlab-Howest/VEooX_plugin
Author: HitLab | Flanders Make
Author-email: HitLab | Flanders Make <sam.van.de.walle@howest.be>
License: MIT
Classifier: Programming Language :: Python :: 3
Classifier: Programming Language :: C++
Classifier: Operating System :: Microsoft :: Windows
Requires-Python: >=3.8
Dynamic: author
Dynamic: home-page
